{
    "/js/app.js": "/js/app.js?id=176c2bcc463e542ff29b",
    "/css/app.css": "/css/app.css?id=e20c820df435c43adfb6",
    "/css/bootstrap.css": "/css/bootstrap.css?id=121b29271ce968aafa9a",
    "/css/bootstrap-ui.css": "/css/bootstrap-ui.css?id=ab487cc327eef0a24b91",
    "/AdminLTE/css/jquery.nestable.css": "/AdminLTE/css/jquery.nestable.css?id=50b9fa0af26057c0d652",
    "/AdminLTE/js/app-admin.js": "/AdminLTE/js/app-admin.js?id=686b09544fd7c6da5bcf",
    "/css/all.css": "/css/all.css?id=fdb4193dcf09162963cf",
    "/js/all.js": "/js/all.js?id=53e98b06770d56681969",
    "/css/colorbox.css": "/css/colorbox.css?id=9bc8833c4d3488f89855",
    "/js/jquery.colorbox.js": "/js/jquery.colorbox.js?id=eb79fa295d1ded56e735"
}
