{
    "/js/app.js": "/js/app.js?id=6725d865c00ee5960e2b",
    "/css/app.css": "/css/app.css?id=23afd118cf5d7b8547d6",
    "/css/bootstrap.css": "/css/bootstrap.css?id=73b81e28003719bbeab9",
    "/css/bootstrap-ui.css": "/css/bootstrap-ui.css?id=aa4a21a7d11a5eebb409",
    "/AdminLTE/js/app-admin.js": "/AdminLTE/js/app-admin.js?id=64efa76853b6c0e4db87",
    "/css/all.css": "/css/all.css?id=40ff25c0ab19faf6d526",
    "/js/all.js": "/js/all.js?id=b4b652a222374c6567cf",
    "/css/colorbox.css": "/css/colorbox.css?id=9bc8833c4d3488f89855",
    "/js/jquery.colorbox.js": "/js/jquery.colorbox.js?id=eb79fa295d1ded56e735"
}
